duplifinder/__init__.py
duplifinder/application.py
duplifinder/ast_processor.py
duplifinder/ast_visitor.py
duplifinder/banner.py
duplifinder/cache.py
duplifinder/cli.py
duplifinder/config.py
duplifinder/definition_finder.py
duplifinder/duplicate_renderer.py
duplifinder/exceptions.py
duplifinder/finder.py
duplifinder/html_renderer.py
duplifinder/main.py
duplifinder/output.py
duplifinder/processor_utils.py
duplifinder/processors.py
duplifinder/refactoring.py
duplifinder/search_finder.py
duplifinder/search_renderer.py
duplifinder/text_finder.py
duplifinder/text_processor.py
duplifinder/token_finder.py
duplifinder/token_processor.py
duplifinder/utils.py
duplifinder/watcher.py
duplifinder-11.0.1.dist-info/METADATA
duplifinder-11.0.1.dist-info/WHEEL
duplifinder-11.0.1.dist-info/entry_points.txt
duplifinder-11.0.1.dist-info/top_level.txt
duplifinder-11.0.1.dist-info/RECORD
