Metadata-Version: 2.4
Name: duplifinder
Version: 11.0.1
Summary: Detect duplicate Python definitions, text patterns, and token similarities for codebase maintainability.
Author-email: Dhruv <dhruv13x@gmail.com>
Maintainer-email: Dhruv <dhruv13x@gmail.com>
License: MIT
Project-URL: Homepage, https://github.com/dhruv13x/duplifinder
Project-URL: Repository, https://github.com/dhruv13x/duplifinder.git
Project-URL: Issues, https://github.com/dhruv13x/duplifinder/issues
Project-URL: Changelog, https://github.com/dhruv13x/duplifinder/blob/main/CHANGELOG.md
Project-URL: Release Notes, https://github.com/dhruv13x/duplifinder/releases
Keywords: code-duplicates,python-ast,refactoring,code-analysis,static-analysis,ci-cd
Classifier: Development Status :: 5 - Production/Stable
Classifier: Intended Audience :: Developers
Classifier: Topic :: Software Development :: Code Generators
Classifier: Topic :: Software Development :: Quality Assurance
Classifier: License :: OSI Approved :: MIT License
Classifier: Operating System :: OS Independent
Classifier: Programming Language :: Python :: 3
Classifier: Programming Language :: Python :: 3.12
Classifier: Programming Language :: Python :: 3 :: Only
Classifier: Typing :: Typed
Requires-Python: >=3.12
Requires-Dist: pyyaml>=6.0
Requires-Dist: rich>=13.0
Requires-Dist: tqdm>=4.66
Requires-Dist: pydantic>=2.5
Requires-Dist: watchdog>=4.0.0
Provides-Extra: dev
Requires-Dist: pytest>=8.0.0; extra == "dev"
Requires-Dist: pytest-cov>=5.0.0; extra == "dev"
Requires-Dist: pytest-timeout>=2.2.0; extra == "dev"
Requires-Dist: pytest-json-report>=1.5.0; extra == "dev"
Requires-Dist: pytest-asyncio>=0.23.0; extra == "dev"
Requires-Dist: pytest-mock>=3.10.0; extra == "dev"
Requires-Dist: pyfakefs>=5.0.0; extra == "dev"
Requires-Dist: ruff>=0.6.0; extra == "dev"
Requires-Dist: black>=24.3.0; extra == "dev"
Requires-Dist: mypy>=1.11.0; extra == "dev"
Requires-Dist: PyYAML>=6.0; extra == "dev"
Requires-Dist: types-PyYAML>=6.0; extra == "dev"
Provides-Extra: docs
Requires-Dist: sphinx>=7.0; extra == "docs"
Requires-Dist: sphinx-rtd-theme>=2.0; extra == "docs"
